{ "rocket_explosion" : { "angleVariance" : 360, "blendFuncDestination" : 771, "blendFuncSource" : 770, "duration" : 0.02999999999999999889, "emitterType" : 0, "finishColor" : "#ffff01", "finishColorAlpha" : 1, "finishColorVariance" : "#00ff01", "finishColorVarianceAlpha" : 1, "finishParticleSize" : 4, "finishParticleSizeVariance" : 0, "gravity" : "2.0, 0.0", "maxParticles" : 22, "maxRadius" : 0, "maxRadiusVariance" : 0, "minRadius" : 0, "minRadiusVariance" : 0, "particleLifespan" : 0, "particleLifespanVariance" : 0.38000000000000000444, "positionType" : 1, "radialAccelVariance" : 0, "radialAcceleration" : 0, "rotatePerSecond" : 0, "rotatePerSecondVariance" : 0, "rotation" : 17, "rotationEnd" : 0, "rotationEndVariance" : 0, "rotationStart" : 0, "rotationStartVariance" : 0, "sourcePositionVariance" : "0.0, 0.0", "speed" : 13, "speedVariance" : 31, "startColor" : "#ffff01", "startColorAlpha" : 1, "startColorVariance" : "#8f0101", "startColorVarianceAlpha" : 1, "startParticleSize" : 0, "startParticleSizeVariance" : 0, "tangentialAccelVariance" : 0, "tangentialAcceleration" : 0, "textureFileName" : "streak.png", "visible" : true, "x" : 0, "y" : 0 } }